mcp_data_analyzer/__init__.py
mcp_data_analyzer/__main__.py
mcp_data_analyzer/cli.py
mcp_data_analyzer/core.py
mcp_data_analyzer-0.8.dist-info/METADATA
mcp_data_analyzer-0.8.dist-info/WHEEL
mcp_data_analyzer-0.8.dist-info/entry_points.txt
mcp_data_analyzer-0.8.dist-info/top_level.txt
mcp_data_analyzer-0.8.dist-info/RECORD
